<?xml version="1.0" encoding="UTF-8"?>
<metadata xml:lang="en"><Esri><CreaDate>20130904</CreaDate><CreaTime>13530300</CreaTime><ArcGISFormat>1.0</ArcGISFormat><SyncOnce>TRUE</SyncOnce><DataProperties><itemProps><itemLocation><linkage Sync="TRUE">file://\\MCG403G31\E$\Mohammad_Lee\BMI_1\BGroup</linkage><protocol Sync="TRUE">Local Area Network</protocol></itemLocation></itemProps><copyHistory><copy source="E:\Mohammad_Lee\BMI\BGroup" dest="\\MCG403G31\E$\Mohammad_Lee\BMI_1\BGroup" date="20130903" time="11555100"></copy></copyHistory><lineage><Process ToolSource="c:\program files (x86)\arcgis\desktop10.1\ArcToolbox\Toolboxes\Data Management Tools.tbx\CalculateField" Date="20130902" Time="155650">CalculateField Age S_T [S_T_1] VB #</Process><Process ToolSource="c:\program files\arcgis\desktop10.2\ArcToolbox\Toolboxes\Data Management Tools.tbx\CalculateField" Date="20130904" Time="130300">CalculateField Working FFood "[DFF] * [POP2011]" VB #</Process><Process ToolSource="c:\program files\arcgis\desktop10.2\ArcToolbox\Toolboxes\Data Management Tools.tbx\CalculateField" Date="20130904" Time="130331">CalculateField Working FFood Int([DFF] * [POP2011] /1000) VB #</Process><Process ToolSource="c:\program files\arcgis\desktop10.2\ArcToolbox\Toolboxes\Data Management Tools.tbx\CalculateField" Date="20130904" Time="130401">CalculateField Working FCntr Int( [D_Fitness] * [POP2011] /1000) VB #</Process><Process ToolSource="c:\program files\arcgis\desktop10.2\ArcToolbox\Toolboxes\Data Management Tools.tbx\CalculateField" Date="20130904" Time="130439">CalculateField Working Fit [S_T] VB #</Process><Process ToolSource="c:\program files\arcgis\desktop10.2\ArcToolbox\Toolboxes\Data Management Tools.tbx\CalculateField" Date="20130904" Time="130506">CalculateField Working NFit "[POP2011] - [Fit]" VB #</Process><Process ToolSource="c:\program files\arcgis\desktop10.2\ArcToolbox\Toolboxes\Data Management Tools.tbx\CalculateField" Date="20130904" Time="130533">CalculateField Working NFit "[1_T] + [2_T] + [3_T]" VB #</Process><Process ToolSource="c:\program files\arcgis\desktop10.2\ArcToolbox\Toolboxes\Data Management Tools.tbx\CalculateField" Date="20130904" Time="130733">CalculateField Working RNorm "[S_T] /( [POP2011] )" VB #</Process><Process ToolSource="c:\program files\arcgis\desktop10.2\ArcToolbox\Toolboxes\Data Management Tools.tbx\CalculateField" Date="20130904" Time="130806">CalculateField Working ROver "[1_T] / [POP2011]" VB #</Process><Process ToolSource="c:\program files\arcgis\desktop10.2\ArcToolbox\Toolboxes\Data Management Tools.tbx\CalculateField" Date="20130904" Time="130828">CalculateField Working ROver "[1_T] / [POP2011]" VB #</Process><Process ToolSource="c:\program files\arcgis\desktop10.2\ArcToolbox\Toolboxes\Data Management Tools.tbx\CalculateField" Date="20130904" Time="130838">CalculateField Working ROver "[1_T] / [POP2011]" VB #</Process><Process ToolSource="c:\program files\arcgis\desktop10.2\ArcToolbox\Toolboxes\Data Management Tools.tbx\CalculateField" Date="20130904" Time="130901">CalculateField Working ROver "[1_T] / [POP2011]" VB #</Process><Process ToolSource="c:\program files\arcgis\desktop10.2\ArcToolbox\Toolboxes\Data Management Tools.tbx\CalculateField" Date="20130904" Time="133240">CalculateField Working SEQID [FID] VB #</Process><Process ToolSource="c:\program files\arcgis\desktop10.2\ArcToolbox\Toolboxes\Data Management Tools.tbx\CalculateField" Date="20130904" Time="134249">CalculateField Working Norm "[POP2011] - [S_T] - [1_T] - [2_T] - [3_T]" VB #</Process><Process ToolSource="c:\program files\arcgis\desktop10.2\ArcToolbox\Toolboxes\Data Management Tools.tbx\CalculateField" Date="20130904" Time="134307">CalculateField Working Overw "[POP2011] - [Norm]" VB #</Process><Process ToolSource="c:\program files\arcgis\desktop10.2\ArcToolbox\Toolboxes\Data Management Tools.tbx\CalculateField" Date="20130904" Time="135039">CalculateField Export_Output E_T "2.4 * [FFood]" VB #</Process><Process ToolSource="c:\program files\arcgis\desktop10.2\ArcToolbox\Toolboxes\Data Management Tools.tbx\CalculateField" Date="20130904" Time="135214">CalculateField Export_Output R_T "4 * [FCntr]" VB #</Process><Process ToolSource="c:\program files\arcgis\desktop10.2\ArcToolbox\Toolboxes\Data Management Tools.tbx\CalculateField" Date="20130906" Time="094704">CalculateField SummitBG ETP 2.4 VB #</Process><Process ToolSource="c:\program files\arcgis\desktop10.2\ArcToolbox\Toolboxes\Data Management Tools.tbx\CalculateField" Date="20130906" Time="094711">CalculateField SummitBG RTP 4 VB #</Process><Process ToolSource="c:\program files\arcgis\desktop10.2\ArcToolbox\Toolboxes\Data Management Tools.tbx\CalculateField" Date="20130906" Time="094754">CalculateField SummitBG ETN "Int ( [E_T] / [ETP]  )" VB #</Process><Process ToolSource="c:\program files\arcgis\desktop10.2\ArcToolbox\Toolboxes\Data Management Tools.tbx\CalculateField" Date="20130906" Time="094836">CalculateField SummitBG RTN "Int ( [R_T] / [RTP] )" VB #</Process></lineage></DataProperties></Esri></metadata>
